startifact/VERSION
startifact/__init__.py
startifact/__main__.py
startifact/artifact.py
startifact/artifact_downloader.py
startifact/artifacts.py
startifact/bucket_names.py
startifact/cli.py
startifact/configuration.py
startifact/configuration_loader.py
startifact/configuration_saver.py
startifact/constants.py
startifact/hash.py
startifact/latest_version_loader.py
startifact/metadata_loader.py
startifact/py.typed
startifact/regional_configuration_deleter.py
startifact/regional_configuration_saver.py
startifact/regional_process.py
startifact/regional_process_result.py
startifact/regional_stager.py
startifact/regions.py
startifact/s3.py
startifact/session.py
startifact/stager.py
startifact/exceptions/__init__.py
startifact/exceptions/cannot_discover_existence.py
startifact/exceptions/cannot_stage_artifact.py
startifact/exceptions/no_configuration.py
startifact/exceptions/no_regions_available.py
startifact/exceptions/no_regions_configured.py
startifact/exceptions/parameter_store.py
startifact/exceptions/project_name.py
startifact/exceptions/py.typed
startifact/parameters/__init__.py
startifact/parameters/bucket.py
startifact/parameters/configuration.py
startifact/parameters/latest_version.py
startifact/parameters/parameter.py
startifact/parameters/py.typed
startifact/tasks/__init__.py
startifact/tasks/arguments.py
startifact/tasks/download.py
startifact/tasks/dry_run.py
startifact/tasks/info.py
startifact/tasks/py.typed
startifact/tasks/setup.asking.yml
startifact/tasks/setup.py
startifact/tasks/stage.py
startifact-1.0a10.dist-info/LICENSE
startifact-1.0a10.dist-info/METADATA
startifact-1.0a10.dist-info/WHEEL
startifact-1.0a10.dist-info/entry_points.txt
startifact-1.0a10.dist-info/top_level.txt
startifact-1.0a10.dist-info/RECORD
