Metadata-Version: 2.1
Name: startifact
Version: 1.0a10
Summary: Stages artifacts into Amazon Web Services
Home-page: https://github.com/cariad/startifact
Author: Cariad Eccleston
Author-email: cariad@cariad.earth
License: MIT
Platform: UNKNOWN
Classifier: Development Status :: 3 - Alpha
Classifier: Environment :: Console
Classifier: License :: OSI Approved :: MIT License
Classifier: Natural Language :: English
Classifier: Operating System :: OS Independent
Classifier: Programming Language :: Python :: 3 :: Only
Classifier: Programming Language :: Python :: 3.10
Classifier: Programming Language :: Python :: 3.8
Classifier: Programming Language :: Python :: 3.9
Classifier: Typing :: Typed
Requires-Python: >=3.8
License-File: LICENSE
Requires-Dist: ansiscape (~=1.0)
Requires-Dist: asking (~=1.0)
Requires-Dist: boto3 (~=1.20)
Requires-Dist: cline (~=1.2)
Requires-Dist: semver (~=2.13)
